xj_behavior/__init__.py
xj_behavior/admin.py
xj_behavior/apps.py
xj_behavior/urls.py
xj_behavior/apis/__init__.py
xj_behavior/apis/contract_integration_apis.py
xj_behavior/apis/customer_statistics_apis.py
xj_behavior/apis/homepage_statistics_apis.py
xj_behavior/apis/standing_book_apis.py
xj_behavior/services/__init__.py
xj_behavior/services/contract_integration_services.py
xj_behavior/services/customer_statistics_services.py
xj_behavior/services/homepage_statistics_services.py
xj_behavior/services/standing_book_services.py
xj_behavior/utils/__init__.py
xj_behavior/utils/custom_authorization.py
xj_behavior/utils/custom_response.py
xj_behavior/utils/custom_tool.py
xj_behavior/utils/execl.py
xj_behavior/utils/j_config.py
xj_behavior/utils/j_dict.py
xj_behavior/utils/j_recur.py
xj_behavior/utils/join_list.py
xj_behavior/utils/model_handle.py
xj_behavior/utils/service_manager.py
xj_behavior/utils/utility_method.py
xj_behavior/utils/validator.py
xj_behavior-1.0.15.dist-info/METADATA
xj_behavior-1.0.15.dist-info/WHEEL
xj_behavior-1.0.15.dist-info/top_level.txt
xj_behavior-1.0.15.dist-info/RECORD
