Metadata-Version: 2.1
Name: xj_behavior
Version: 1.0.15
Summary: 行为模块
License: apache 3.0
